magicline/__init__.py
magicline/__main__.py
magicline/decorators/singleton.py
magicline-0.1.1.dist-info/WHEEL
magicline-0.1.1.dist-info/entry_points.txt
magicline-0.1.1.dist-info/METADATA
magicline-0.1.1.dist-info/RECORD
