Metadata-Version: 2.3
Name: magicline
Version: 0.1.1
Summary: Add your description here
Author: lipanpan
Author-email: lipanpan <lipanpanmail@163.com>
Requires-Dist: fire>=0.7.1
Requires-Dist: pyperclip>=1.11.0
Requires-Dist: toml>=0.10.2
Requires-Python: ~=3.13.0
